gpcam/__init__.py
gpcam/_version.py
gpcam/autonomous_experimenter.py
gpcam/deep_kernel_network.py
gpcam/gp_mcmc.py
gpcam/gp_optimizer.py
gpcam/gp_optimizer_base.py
gpcam/kernels.py
gpcam/surrogate_model.py
gpcam-8.3.6.dist-info/METADATA
gpcam-8.3.6.dist-info/WHEEL
gpcam-8.3.6.dist-info/licenses/AUTHORS.md
gpcam-8.3.6.dist-info/licenses/COPYING
gpcam-8.3.6.dist-info/licenses/LICENSE
gpcam-8.3.6.dist-info/RECORD
