Metadata-Version: 2.4
Name: gpcam
Version: 8.3.6
Summary: Autonomous data acquisition
Project-URL: Homepage, https://gpcam.lbl.gov
Project-URL: Documentation, https://gpcam.readthedocs.io/
Project-URL: Repository, https://github.com/lbl-camera/gpcam.git
Project-URL: Bug Tracker, https://github.com/lbl-camera/gpcam/issues
Project-URL: Changelog, https://github.com/lbl-camera/gpcam/commits/master/
Author-email: Marcus Michael Noack <MarcusNoack@lbl.gov>, "Ronald J. Pandolfi" <ronpandolfi@lbl.gov>
Maintainer-email: Marcus Michael Noack <MarcusNoack@lbl.gov>, "Ronald J. Pandolfi" <ronpandolfi@lbl.gov>
License: *** License Agreement ***
License-File: AUTHORS.md
License-File: COPYING
License-File: LICENSE
Keywords: adaptive,autonomous,bayesian optimization,gaussian process,self driving
Classifier: Development Status :: 5 - Production/Stable
Classifier: Intended Audience :: Developers
Classifier: License :: OSI Approved :: GNU General Public License v3 or later (GPLv3+)
Classifier: Natural Language :: English
Classifier: Programming Language :: Python :: 3
Classifier: Programming Language :: Python :: 3.11
Classifier: Programming Language :: Python :: 3.12
Requires-Python: >=3.11
Requires-Dist: dask~=2025.5.1
Requires-Dist: distributed~=2025.5.1
Requires-Dist: fvgp>=4.7.8
Requires-Dist: loguru
Requires-Dist: numpy~=2.2.6
Requires-Dist: scipy~=1.16.0
Requires-Dist: wheel
Provides-Extra: docs
Requires-Dist: autodocs; extra == 'docs'
Requires-Dist: myst-nb; extra == 'docs'
Requires-Dist: myst-parser; extra == 'docs'
Requires-Dist: sphinx-hoverxref; extra == 'docs'
Requires-Dist: sphinx-immaterial; extra == 'docs'
Requires-Dist: sphinx-panels; extra == 'docs'
Requires-Dist: sphinx<9; extra == 'docs'
Provides-Extra: plotting
Requires-Dist: matplotlib; extra == 'plotting'
Requires-Dist: notebook; extra == 'plotting'
Requires-Dist: plotly; extra == 'plotting'
Provides-Extra: tests
Requires-Dist: codecov; extra == 'tests'
Requires-Dist: imate; extra == 'tests'
Requires-Dist: pytest; extra == 'tests'
Requires-Dist: pytest-cov; extra == 'tests'
Requires-Dist: torch; extra == 'tests'
